foxlator_lib/__init__.py
foxlator_lib/audio.py
foxlator_lib/error.py
foxlator_lib/py.typed
foxlator_lib/video.py
foxlator_lib/stt/__init__.py
foxlator_lib/stt/whisper_stt.py
foxlator_lib/utils/__init__.py
foxlator_lib-0.10.0.dist-info/METADATA
foxlator_lib-0.10.0.dist-info/WHEEL
foxlator_lib-0.10.0.dist-info/licenses/LICENSE
foxlator_lib-0.10.0.dist-info/RECORD
